clp_ffi_py-0.0.14.dist-info/RECORD
clp_ffi_py-0.0.14.dist-info/WHEEL
clp_ffi_py-0.0.14.dist-info/METADATA
clp_ffi_py-0.0.14.dist-info/licenses/LICENSE
clp_ffi_py/__init__.py
clp_ffi_py/utils.py
clp_ffi_py/py.typed
clp_ffi_py/wildcard_query.py
clp_ffi_py/ir/native_deprecated.py
clp_ffi_py/ir/readers.py
clp_ffi_py/ir/query_builder.py
clp_ffi_py/ir/__init__.py
clp_ffi_py/ir/native.cpython-38-darwin.so
clp_ffi_py/ir/py.typed
clp_ffi_py/ir/native.pyi
