Metadata-Version: 2.1
Name: clp_ffi_py
Version: 0.0.14
Summary: Python interface to the CLP Core Features through CLP's FFI
Author-Email: zhihao lin <lin.zhihao@yscope.com>
License: Apache License 2.0
Classifier: License :: OSI Approved :: Apache Software License
Project-URL: Homepage, https://github.com/y-scope/clp-ffi-py
Project-URL: Bug tracker, https://github.com/y-scope/clp-ffi-py/issues
Requires-Python: >=3.7
Requires-Dist: Deprecated>=1.2.14
Requires-Dist: msgpack==1.0.5
Requires-Dist: python-dateutil>=2.7.0
Requires-Dist: typing-extensions>=4.1.1
Requires-Dist: zstandard>=0.18.0
